setuptools_download.py
setuptools_download-1.1.0.dist-info/LICENSE
setuptools_download-1.1.0.dist-info/METADATA
setuptools_download-1.1.0.dist-info/WHEEL
setuptools_download-1.1.0.dist-info/entry_points.txt
setuptools_download-1.1.0.dist-info/top_level.txt
setuptools_download-1.1.0.dist-info/RECORD
