Metadata-Version: 2.1
Name: setuptools-download
Version: 1.1.0
Summary: setuptools plugin to download external files
Home-page: https://github.com/asottile/setuptools-download
Author: Anthony Sottile
Author-email: asottile@umich.edu
License: MIT
Classifier: License :: OSI Approved :: MIT License
Classifier: Programming Language :: Python :: 3
Classifier: Programming Language :: Python :: 3 :: Only
Classifier: Programming Language :: Python :: Implementation :: CPython
Classifier: Programming Language :: Python :: Implementation :: PyPy
Requires-Python: >=3.8
License-File: LICENSE
Requires-Dist: setuptools (>=46.1.0)
